[{"id":1,"name":"Raja","mailId":"raja@gmail.com","contactNumber":9530068726,"projects":[{"id":1,"name":"Airline Reservation","description":"Java based App"},{"id":1,"name":"Airline Reservation","description":"Java based App"},{"id":1,"name":"Airline Reservation","description":"Java based App"}]},{"id":2,"name":"Rani","mailId":"rani@gmail.com","contactNumber":9530068726,"projects":[{"id":1,"name":"Airline Reservation","description":"Java based App"},{"id":1,"name":"Airline Reservation","description":"Java based App"},{"id":1,"name":"Airline Reservation","description":"Java based App"}]},{"id":3,"name":"Ravi","mailId":"ravi@gmail.com","contactNumber":9530068726,"projects":[{"id":1,"name":"Airline Reservation","description":"Java based App"},{"id":1,"name":"Airline Reservation","description":"Java based App"},{"id":1,"name":"Airline Reservation","description":"Java based App"}]}]